aiomax/__init__.py
aiomax/bot.py
aiomax/buttons.py
aiomax/cache.py
aiomax/exceptions.py
aiomax/filters.py
aiomax/fsm.py
aiomax/router.py
aiomax/types.py
aiomax/utils.py
aiomax-2.12.3.dist-info/licenses/LICENSE.md
aiomax-2.12.3.dist-info/METADATA
aiomax-2.12.3.dist-info/WHEEL
aiomax-2.12.3.dist-info/top_level.txt
aiomax-2.12.3.dist-info/RECORD
